pysafeguard.py
pysafeguard-7.4.0.dist-info/LICENSE
pysafeguard-7.4.0.dist-info/METADATA
pysafeguard-7.4.0.dist-info/WHEEL
pysafeguard-7.4.0.dist-info/RECORD
