Metadata-Version: 2.1
Name: pysafeguard
Version: 7.4.0
Summary: One Identity Safeguard Python Package
Home-page: https://github.com/OneIdentity/PySafeguard
Keywords: safeguard,oneidentity
Author: Tania Engel
Author-email: Tania.Engel@oneidentity.com
Maintainer: Stephanie Zinn
Maintainer-email: Stephanie.Zinn@oneidentity.com
Requires-Python: >=3.7,<4.0
Classifier: License :: OSI Approved :: Apache Software License
Classifier: Operating System :: OS Independent
Classifier: Programming Language :: Python :: 3
Classifier: Programming Language :: Python :: 3.7
Classifier: Programming Language :: Python :: 3.8
Classifier: Programming Language :: Python :: 3.9
Classifier: Programming Language :: Python :: 3.10
Classifier: Programming Language :: Python :: 3.11
Provides-Extra: signalr
Requires-Dist: requests (>=2.28.1,<3.0.0)
Requires-Dist: signalrcore (>=0.9.5,<0.10.0) ; extra == "signalr"
Project-URL: Bug Tracker, https://github.com/OneIdentity/PySafeguard/issues
Project-URL: Repository, https://github.com/OneIdentity/PySafeguard
